{
  "items": [
    {
      "slug": "enter-the-pixar-brain-trust-with-inside-out-2-writer-meg-lefauve-2024",
      "date": "2024-06-18",
      "published_at": "2024-06-18T00:00:00Z",
      "created_at": "2024-06-18T00:00:00Z",
      "title": "Enter the Pixar Brain Trust with ‘Inside Out 2’ Writer Meg LeFauve",
      "cover": "https://www.indiewire.com/wp-content/uploads/2024/01/MCDINOU_WD002.jpg?w=1600",
      "canonical": "https://archive.aventuroo.com/entertainment/general/enter-the-pixar-brain-trust-with-inside-out-2-writer-meg-lefauve-2024/",
      "excerpt": "Inside Out 2 Writer Meg LeFauve Explains the Pixar Brain Trust × Got a Tip? Newsletters Open Menu Close News Film TV Awards Video Future of Filmmaking Search Icon Open Search Close Read Next: Jessica Chastain Says She’s ‘Not Aligned’ with Apple on ‘The Savant’ Delay Newsletter…",
      "source": "https://www.indiewire.com/film/film/inside-out-2-writer-meg-lefauve-pixar-brain-trust-1235017147/",
      "contact_url": "https://www.aventuroo.com/contact"
    }
  ],
  "count": 1,
  "updated_at": "2024-06-18",
  "pagination": {
    "total_items": 1,
    "per_page": 12,
    "total_pages": 1
  }
}
